[{"domain":".www.automationpractice.pl","expiry":1750882920.390318,"goog:priority":"Medium","goog:sameParty":false,"goog:session":false,"goog:sourcePort":80,"goog:sourceScheme":"NonSecure","httpOnly":true,"name":"PrestaShop-2ae4d32f6206717abc31030c0cc08275","path":"/","sameSite":"none","secure":false,"size":603,"value":"fMQcpHD0y6I%3DCOvgZDcGJzY%3D3iQxYVWNhUw%3DSAncL%2FiXLq8%3DV2yp%2BLfvm1E%3D4%2FYAspTMqAk%3DRMT6wdoS4uk%3D2i7n2hAoRy0%3DEppubeBqT1U%3D96n6Lx4wLgs%3DfKGDfwTwp0s%3DqkvIeuKT6E4%3DgwnaoKVUn5k%3DcOOYs0eyu0s%3D0igdk22HYuE%3DCF%2BtCfubny8%3DnrZHCvQF%2Fbc%3DwjelH4P1VI4%3DIoiSxlZB56o%3D%2Bbgr7VOgUOQ%3DqWGzvS7uu%2Bs%3DidmzWHHrlEA%3DtXrnqcGGBvQ%3DctX0eTL59CA%3DiTBvtoeKGFw%3DOg0lFPttxn8%3DfRtOq1ljq54%3D6tvSIgYyszA%3DP%2BDdQqNaiQc%3Dx1DroWT7YfU%3DDlGTSa8Tnzw%3Dgqjp1PJ2%2B04%3DAHiIPmavbIM%3DsdRBYkD4h1c%3Dvnq%2Bdt7KhHE%3DwSrx9Jx0rJs%3DCDPGctP8km4%3DduB%2FSsQj9JM%3D000301"}]